<?xml version="1.0" encoding="utf-8"?>
<search>
  
  
  
  <entry>
    <title>第5周总结</title>
    <link href="/2022/04/03/%E7%AC%AC5%E5%91%A8%E6%80%BB%E7%BB%93/"/>
    <url>/2022/04/03/%E7%AC%AC5%E5%91%A8%E6%80%BB%E7%BB%93/</url>
    
    <content type="html"><![CDATA[<p>上课好好听了，阅读和听力基本上坚持下来了</p><p>单词好好背了</p><p>有氧和力量训练都做了</p><p>回了躺家，吃了点好吃的</p><p>接触了一个搞项目的，深度学习，抓住这个机会好好学习一波，不过居然是个女的，交流不方便</p><p>下周坚持，继续加油！</p>]]></content>
    
    
    <categories>
      
      <category>大三下</category>
      
    </categories>
    
    
  </entry>
  
  
  
  <entry>
    <title>第4周总结</title>
    <link href="/2022/03/29/%E7%AC%AC4%E5%91%A8%E6%80%BB%E7%BB%93/"/>
    <url>/2022/03/29/%E7%AC%AC4%E5%91%A8%E6%80%BB%E7%BB%93/</url>
    
    <content type="html"><![CDATA[<p>单词背了</p><p>运动做了</p><p>课听了</p><p>就是听力没听……</p><p>想的有点多</p><p>满分10分我给5分</p>]]></content>
    
    
    <categories>
      
      <category>大三下</category>
      
    </categories>
    
    
  </entry>
  
  
  
  <entry>
    <title>第3周总结</title>
    <link href="/2022/03/20/%E7%AC%AC3%E5%91%A8%E6%80%BB%E7%BB%93/"/>
    <url>/2022/03/20/%E7%AC%AC3%E5%91%A8%E6%80%BB%E7%BB%93/</url>
    
    <content type="html"><![CDATA[<p>这周状态开始逐渐恢复了，校赛也成功办完了，报销也提交了，可以说没啥要忙的了。</p><p>单词有子背，不过有点水，其次阅读也是三天打鱼两天晒网，这周得好好努力，坚持下来。</p><p>听力也得开始了，然后编程方面也开始恢复了，通过对一些常规代码的学习，进步的也很快。</p><p>这周给自己打80分</p><p>下周目标</p><ul><li>单词坚持</li><li>跑步or跳绳</li><li>阅读+听力</li><li>认真上网课</li><li>代码好好敲</li></ul><p>believe yourself and be brave</p>]]></content>
    
    
    <categories>
      
      <category>大三下</category>
      
    </categories>
    
    
  </entry>
  
  
  
  <entry>
    <title>开学反思和后续计划</title>
    <link href="/2022/03/17/%E5%BC%80%E5%AD%A6%E5%8F%8D%E6%80%9D%E5%92%8C%E5%90%8E%E7%BB%AD%E8%AE%A1%E5%88%92/"/>
    <url>/2022/03/17/%E5%BC%80%E5%AD%A6%E5%8F%8D%E6%80%9D%E5%92%8C%E5%90%8E%E7%BB%AD%E8%AE%A1%E5%88%92/</url>
    
    <content type="html"><![CDATA[<p>开学到现在是第三周了，从考完试到现在基本上没怎么学，问题很大，浪费了很多时间。</p><h3 id="现在梳理一下要干的事情："><a href="#现在梳理一下要干的事情：" class="headerlink" title="现在梳理一下要干的事情："></a>现在梳理一下要干的事情：</h3><p>1.英语</p><p>2.赶上各门课程的进度+完成作业</p><p>3.准备校赛，以后后续的工作</p><p>4.锻炼</p><h3 id="分析："><a href="#分析：" class="headerlink" title="分析："></a>分析：</h3><p>首先这是保研的最后一学期了，我应该在这学期提高英语水平，保持绩点，学习py，搞搞神经网络。因此这学期还是很重要的。</p><h3 id="解决途径："><a href="#解决途径：" class="headerlink" title="解决途径："></a>解决途径：</h3><p>1.不折不扣的每天背一个小时单词+做阅读一篇，一周一套听力</p><p>2.少打游戏多听课+网课</p><p>3.把事干好就行</p><p>4.坚持跑步or跳绳，+哑铃训练</p><h3 id="最后："><a href="#最后：" class="headerlink" title="最后："></a>最后：</h3><p>尽快把状态调整过来，好好学习，天天向上</p>]]></content>
    
    
    <categories>
      
      <category>碎碎念</category>
      
    </categories>
    
    
  </entry>
  
  
  
  <entry>
    <title>第2周总结</title>
    <link href="/2022/03/13/%E7%AC%AC2%E5%91%A8%E6%80%BB%E7%BB%93/"/>
    <url>/2022/03/13/%E7%AC%AC2%E5%91%A8%E6%80%BB%E7%BB%93/</url>
    
    <content type="html"><![CDATA[<p> 开学的第二周，上课的第一周，除了网课编译原理外，其他课都有好好听</p><p>每天都坚持跑步了，单词背的妈妈虎虎</p><p>三门考试出来了俩门，计组92，数据库96，考的还可以，希望计网也有一个不错的成绩</p><h2 id="后续计划"><a href="#后续计划" class="headerlink" title="后续计划"></a>后续计划</h2><ul><li>单词每天100+</li><li>跑步有氧+哑铃无氧</li><li>认真看网课+作业</li><li>开始深度学习，理论+实践</li></ul><p>加油，最后一学期了，维持绩点，看能不能把国奖给安排了，做点项目，六级考个好分数</p>]]></content>
    
    
    <categories>
      
      <category>大三下</category>
      
    </categories>
    
    
  </entry>
  
  
  
  <entry>
    <title>寒假过半总结</title>
    <link href="/2022/02/15/%E5%AF%92%E5%81%87%E8%BF%87%E5%8D%8A%E6%80%BB%E7%BB%93/"/>
    <url>/2022/02/15/%E5%AF%92%E5%81%87%E8%BF%87%E5%8D%8A%E6%80%BB%E7%BB%93/</url>
    
    <content type="html"><![CDATA[<ul><li><p>学习方面</p><p>对人工智能有了个基本的认识，单词隔三岔五的背,复习了，但又没完全复习</p></li><li><p>运动方面</p><p>每天都有坚持跳绳，脸比以前瘦多来，也开始注重护肤了</p></li><li><p>生活方面</p><p>出去玩的很开心，人果然是群居性的动物呢</p><h2 id="总的来说"><a href="#总的来说" class="headerlink" title="总的来说"></a>总的来说</h2><p>还行吧，至少没有完全虚度光阴</p></li></ul>]]></content>
    
    
    <categories>
      
      <category>大三寒假</category>
      
    </categories>
    
    
  </entry>
  
  
  
  <entry>
    <title>回家第一周总结</title>
    <link href="/2022/01/27/%E5%9B%9E%E5%AE%B6%E7%AC%AC%E4%B8%80%E5%91%A8%E6%80%BB%E7%BB%93/"/>
    <url>/2022/01/27/%E5%9B%9E%E5%AE%B6%E7%AC%AC%E4%B8%80%E5%91%A8%E6%80%BB%E7%BB%93/</url>
    
    <content type="html"><![CDATA[<p>回家一周了，和想象中的生活有点区别，但也不错。</p><p>坚持跳绳！</p><p>坚持吃早饭！</p><p>英语断断续续的买单词了，这点不行。</p><p>吃了好几顿好吃的。</p><p>但这段时间过的有点空虚，从下周开始必需得给自己找点事干，让自己充实起来。</p><p>目前想法是这样：</p><p>单词+健身是固定的，雷打不动。</p><p>然后把画时间把手写数字识别给整完。</p><p>完了开始复习下学期要学的东西。</p><p>假期感觉也不是很长啊。下个月25左右就得回学校了，呜呜呜。</p><p>寒假，我滴寒假。</p>]]></content>
    
    
    <categories>
      
      <category>大三寒假</category>
      
    </categories>
    
    
  </entry>
  
  
  
  <entry>
    <title>2022.1.15</title>
    <link href="/2022/01/15/2022-1-15/"/>
    <url>/2022/01/15/2022-1-15/</url>
    
    <content type="html"><![CDATA[<p>本来好好的，打算随便学学数据分析等放假了。甚至比起周围的人，自己每天都有学习，锻炼，饮食也比较规律，比较沾沾自喜。认为自己还比较自律。</p><p>但是人比人，比不了，当我在混日子时候，有的人在和老师搞项目，有的人在准备雅思，托福，还有的人在为发论文做准备，而我呢，像一滩死水一样。</p><p>还不是时候，还得卷，为了让自己的一天过的充实，制定每日必须完成的任务。</p><ul><li><p>一日三餐，蛋白质，碳水，维生素</p></li><li><p>每天跳绳，胸or腹一组</p></li><li><p>英语学习时间&gt;=1h</p></li><li><p>其他学习时间&gt;=4.5h</p><p>就先这样了，这也是对自己的一种约束，对我自己一种压力，同时也是对自己负责。</p><p>believe yourself and be brave</p></li></ul>]]></content>
    
    
    <categories>
      
      <category>碎碎念</category>
      
    </categories>
    
    
  </entry>
  
  
  
  <entry>
    <title>大三上总结，到开学前安排</title>
    <link href="/2022/01/13/%E5%A4%A7%E4%B8%89%E4%B8%8A%E6%80%BB%E7%BB%93%EF%BC%8C%E5%88%B0%E5%BC%80%E5%AD%A6%E5%89%8D%E5%AE%89%E6%8E%92/"/>
    <url>/2022/01/13/%E5%A4%A7%E4%B8%89%E4%B8%8A%E6%80%BB%E7%BB%93%EF%BC%8C%E5%88%B0%E5%BC%80%E5%AD%A6%E5%89%8D%E5%AE%89%E6%8E%92/</url>
    
    <content type="html"><![CDATA[<p>这学期过的好快啊，转眼间，以及快结束了。</p><p>总的来说，这学期还可以，绩点提高了好多，现在是4.21，有了第一个女朋友，健身有一点点效果，单词有在好好背，如果六级能过那就再好不过了。</p><p>对自己说</p><p><strong>干得漂亮，李正曦</strong></p><p>后续，坚持锻炼，坚持英语。</p><p>然后把数据分析，数据挖掘学一学。</p><p>熟练py的一些语法。</p><p>然后复习没考完的三门课，争取满绩，直接把绩点拉满。</p><p>咬咬牙，最后一个学期了。</p><p>付出就会有回报。</p>]]></content>
    
    
    <categories>
      
      <category>碎碎念</category>
      
    </categories>
    
    
  </entry>
  
  
  
  <entry>
    <title>第19周总结</title>
    <link href="/2022/01/13/%E7%AC%AC19%E5%91%A8%E6%80%BB%E7%BB%93/"/>
    <url>/2022/01/13/%E7%AC%AC19%E5%91%A8%E6%80%BB%E7%BB%93/</url>
    
    <content type="html"><![CDATA[<p>这周完成了网络的课设，剩下时间处于复习与不复习的量子态，最后考试推迟到春季学期开学考，麻了，白复习了。</p><p>但好在开始坚持在宿舍锻炼了。</p><p>这学期算是结束了吧，就等着放假回家了。</p>]]></content>
    
    
    <categories>
      
      <category>大三上</category>
      
    </categories>
    
    
  </entry>
  
  
  
  <entry>
    <title>第17周总结</title>
    <link href="/2022/01/02/%E7%AC%AC17%E5%91%A8%E6%80%BB%E7%BB%93/"/>
    <url>/2022/01/02/%E7%AC%AC17%E5%91%A8%E6%80%BB%E7%BB%93/</url>
    
    <content type="html"><![CDATA[<p>疫情在宿舍的一周，摸鱼复习，课设，打游戏。</p><p>运动少了，学习时间也少了。</p><p>感觉有点浪费时间了。</p><p>下周开始，恢复学习作息，坚持运动，坚持背单词。</p><p>课设好好弄，好好复习。</p><p>给这学期画上完美的句号。</p>]]></content>
    
    
    <categories>
      
      <category>大三上</category>
      
    </categories>
    
    
  </entry>
  
  
  
  <entry>
    <title>第15周总结</title>
    <link href="/2021/12/19/%E7%AC%AC15%E5%91%A8%E6%80%BB%E7%BB%93/"/>
    <url>/2021/12/19/%E7%AC%AC15%E5%91%A8%E6%80%BB%E7%BB%93/</url>
    
    <content type="html"><![CDATA[<p>中规中矩的一周，跳绳+单词+复习+打游戏</p><p>六级能不能过看运气，过也可能刚过线（那还是过吧）</p><p>然后没啥好说的。</p><p>这学期还有5门考试。</p><p>明天考操作系统和java</p><p>复习了好多，但感觉又啥都不会。</p><p>希望操作系统能上90。</p><p>java能上93.</p><p>呜呜呜呜呜呜呜呜呜呜呜，我是fw</p>]]></content>
    
    
    <categories>
      
      <category>大三上</category>
      
    </categories>
    
    
  </entry>
  
  
  
  <entry>
    <title>第14周总结</title>
    <link href="/2021/12/12/%E7%AC%AC14%E5%91%A8%E6%80%BB%E7%BB%93/"/>
    <url>/2021/12/12/%E7%AC%AC14%E5%91%A8%E6%80%BB%E7%BB%93/</url>
    
    <content type="html"><![CDATA[<p>周一图形学成绩出来了，98，专业第一，好耶。</p><p>软工成绩明天出，希望能93+，信号与系统还没消息，好麻烦。</p><p>csp认证205，2创新学分到手，舒服了。</p><p>每天坚持背单词了，不过课少，作业少，然后复习起来没头绪，游戏时间稍微有点多了，不应该。</p><p>有在坚持运动和跳绳，卓有成效。</p><p>周内和雄雄吃了kfc，和朋友吃了酸菜鱼。</p><p>周末和学长吃了一顿，和高中朋友吃了一顿。</p><p>吃美了，隔~</p>]]></content>
    
    
    <categories>
      
      <category>大三上</category>
      
    </categories>
    
    
  </entry>
  
  
  
  <entry>
    <title>2021.12.10</title>
    <link href="/2021/12/10/2021-12-10/"/>
    <url>/2021/12/10/2021-12-10/</url>
    
    <content type="html"><![CDATA[<p>上午在网络实验室做实验，累了，出来活动，楼外的景色一览无余。</p><p>中午吃完饭，回到了地下室，一个人都没。</p><p>雄雄退役以后就再没来过了。</p><p>徐诚这几天身体不舒服，没来。</p><p>吴世杰不知道在忙什么，没来。</p><p>钱坤不知道干什么，没来。</p><p>学累了，抬头一看，啥也没有，看吐了。</p><p>这种破日子还得过多久。我什么时候才能离开地下室，见到外面的阳光呢。</p><p>捡起笔，还得学。希望这一天早点来吧</p>]]></content>
    
    
    <categories>
      
      <category>碎碎念</category>
      
    </categories>
    
    
  </entry>
  
  
  
  <entry>
    <title>第13周总结</title>
    <link href="/2021/12/05/%E7%AC%AC13%E5%91%A8%E6%80%BB%E7%BB%93/"/>
    <url>/2021/12/05/%E7%AC%AC13%E5%91%A8%E6%80%BB%E7%BB%93/</url>
    
    <content type="html"><![CDATA[<p>这一周坚持背单词了，每天也有在锻炼。</p><p>把实验报告能写的全写完了。</p><p>周天下午csp有点蛋疼，评测机半天跑不出来，心态有点崩，第二题式子推了半天，感觉推错了，没管，后面的题写了暴力交了，但愿能骗到分，希望最后能上个200分。</p><p>成绩现在还看不到，可能是最近要评教的原因。</p><p>emmmm。</p><p>等下回宿舍，想下后面俩周的安排。</p><p>毕竟马上就是六级，省赛，英语。还得全力以赴。</p>]]></content>
    
    
    <categories>
      
      <category>大三上</category>
      
    </categories>
    
    
  </entry>
  
  
  
  <entry>
    <title>第12周总结</title>
    <link href="/2021/11/28/%E7%AC%AC12%E5%91%A8%E6%80%BB%E7%BB%93/"/>
    <url>/2021/11/28/%E7%AC%AC12%E5%91%A8%E6%80%BB%E7%BB%93/</url>
    
    <content type="html"><![CDATA[<p>规律的一周，背单词，学英语，复习考试。</p><p>每天坚持锻炼了，真不错。</p><p>单词已经快70天打卡了，赞。</p><p>认识了好几个有趣且实力强的网友，敬佩和向往。</p><p>认真复习了几天，拿下，图形学应该95+，软工90+？，看老师改的松不松了。</p><p>刚和舍友吃点烧烤喝点酒，写完总结，还得写计组作业。明天还得交。</p><p>后面还有五门考试，csp认证，六级，各种实验，各种报告。但刚考完试的我感觉非常的轻松。</p><p>保持这个状态到寒假。</p><p>收拾好自己的花园。</p>]]></content>
    
    
    <categories>
      
      <category>大三上</category>
      
    </categories>
    
    
  </entry>
  
  
  
  <entry>
    <title>第十一周总结</title>
    <link href="/2021/11/21/%E7%AC%AC%E5%8D%81%E4%B8%80%E5%91%A8%E6%80%BB%E7%BB%93/"/>
    <url>/2021/11/21/%E7%AC%AC%E5%8D%81%E4%B8%80%E5%91%A8%E6%80%BB%E7%BB%93/</url>
    
    <content type="html"><![CDATA[<p>随着第十一周的结束，马上就要开始连续考试的日子了。最近得好好复习，全力以赴。</p><p>这周，每天坚持跑步，背单词，早起。</p><p>健康作息，给自己点赞。</p><p>为了听杰伦的歌，特意下了qq音乐，还开了会员，真有你的。</p><p>从大一开始，我都活在她给的梦里。</p><p>梦醒了吗？没有醒。</p><p>她就像远方的灯塔一样，穿过层层迷雾，将光打在我身上。</p><p>而我也将向着光航行，不关结果如果</p><p>享受这个过程，享受现在就行了</p>]]></content>
    
    
    <categories>
      
      <category>大三上</category>
      
    </categories>
    
    
  </entry>
  
  
  
  <entry>
    <title>第10周总结</title>
    <link href="/2021/11/15/%E7%AC%AC10%E5%91%A8%E6%80%BB%E7%BB%93/"/>
    <url>/2021/11/15/%E7%AC%AC10%E5%91%A8%E6%80%BB%E7%BB%93/</url>
    
    <content type="html"><![CDATA[<p>济南打铁退役，一题快铜，高斯消元取模，实力和运气都差点。</p><p>每天归规律律，学习跑步单词上课睡觉。</p><p>感觉节奏还行，后续把敲代码时间交给英语和py，加油。付出多少，收获多少</p>]]></content>
    
    
    <categories>
      
      <category>大三上</category>
      
    </categories>
    
    
  </entry>
  
  
  
  <entry>
    <title>第九周总结</title>
    <link href="/2021/11/07/%E7%AC%AC%E4%B9%9D%E5%91%A8%E6%80%BB%E7%BB%93/"/>
    <url>/2021/11/07/%E7%AC%AC%E4%B9%9D%E5%91%A8%E6%80%BB%E7%BB%93/</url>
    
    <content type="html"><![CDATA[<p>抑郁了几天，崩溃了几天，哭了好几次。这学期过了一半了，希望能好好把握剩下的半学期</p><p>课好好听了，网课刷了，单词背了，每天坚持2km。</p><p>信号与系统大意了，完全没有准备，歇逼了，希望老师能捞一手</p>]]></content>
    
    
    <categories>
      
      <category>大三上</category>
      
    </categories>
    
    
  </entry>
  
  
  
  <entry>
    <title>第八周总结</title>
    <link href="/2021/10/31/%E7%AC%AC%E5%85%AB%E5%91%A8%E6%80%BB%E7%BB%93/"/>
    <url>/2021/10/31/%E7%AC%AC%E5%85%AB%E5%91%A8%E6%80%BB%E7%BB%93/</url>
    
    <content type="html"><![CDATA[<p>周一到周四，按部就班，周四晚上和舍友出去吃了河底捞（隔</p><p>周五晚上打了牛客练习赛，3道题签完光速跑路，其实第四题是可以写的，下次跑晚点。</p><p>周六，睡到9点，等到地下室已经10点了，早上看网课，中午睡了一会，下午听了一套听力，算下分108.</p><p>晚上打了cf，回去12点半了，上蓝了，expert！好耶</p><p>周天常规作息，下午开了长辽宁省赛，7题结束，银区了。然后看了会题回宿舍。</p><p>ps：好想当个女生。</p><p>信号与系统还有5天考试，济南站14天。</p><p>加油！</p>]]></content>
    
    
    <categories>
      
      <category>大三上</category>
      
    </categories>
    
    
  </entry>
  
  
  
  <entry>
    <title>第七周总结</title>
    <link href="/2021/10/24/%E7%AC%AC%E4%B8%83%E5%91%A8%E6%80%BB%E7%BB%93/"/>
    <url>/2021/10/24/%E7%AC%AC%E4%B8%83%E5%91%A8%E6%80%BB%E7%BB%93/</url>
    
    <content type="html"><![CDATA[<p>这周开始了三点一线的生活，宿舍，教室-地下室，图书馆。</p><p>早上早起去教室背单词，然后上课。</p><p>中午去北门吃饭，然后睡15-22min，去地下室呆一会，然后上课。</p><p>晚上去食堂随便吃吃，然后去地下室，eng+code，差不多了去操场，跑步，然后回宿舍练一下，睡觉。</p><p>这一周，英语学习没落实到位，睡眠质量不是很好，上课有时候会犯困。</p><p>下一周争取完成目标</p>]]></content>
    
    
    <categories>
      
      <category>大三上</category>
      
    </categories>
    
    
  </entry>
  
  
  
  <entry>
    <title>最近</title>
    <link href="/2021/10/19/%E6%9C%80%E8%BF%91/"/>
    <url>/2021/10/19/%E6%9C%80%E8%BF%91/</url>
    
    <content type="html"><![CDATA[<p>上课和之前一样，正常听课就行，注意网课赶进度和作业的完成。</p><p>求求你认真完成目标，不要光背单词，然后逃避做题，那都是钱啊！！</p><p>提高课整快点</p><p>跑步没问题，keep一回到宿舍就不想搞，想摸鱼，赶紧改</p><p>让自己忙起来，忙起来就不会想了，这个月过去就好了。</p><p>目光看远一点，提升自己才是最重要的。尽人事！</p>]]></content>
    
    
    <categories>
      
      <category>杂</category>
      
    </categories>
    
    
  </entry>
  
  
  
  <entry>
    <title>大三规划</title>
    <link href="/2021/10/13/%E5%A4%A7%E4%B8%89%E8%A7%84%E5%88%92/"/>
    <url>/2021/10/13/%E5%A4%A7%E4%B8%89%E8%A7%84%E5%88%92/</url>
    
    <content type="html"><![CDATA[<h3 id="绩点"><a href="#绩点" class="headerlink" title="绩点"></a>绩点</h3><p>结合上课和网课，上课没搞明白的课下尽快解决，不要拖延。</p><p>消息灵通，注意考试的的信息。</p><p>完整老师要求的作业。</p><h3 id="六级"><a href="#六级" class="headerlink" title="六级"></a>六级</h3><p>每天早起背单词。</p><p>四天听一套听力。</p><p>2天完成一套阅读（俩篇仔细阅读和长篇阅读）。</p><h3 id="竞赛"><a href="#竞赛" class="headerlink" title="竞赛"></a>竞赛</h3><p>有比赛就打，完了补题，acwing提高课搞起来。</p><p>一天1.5~2.5h</p><h3 id="身体"><a href="#身体" class="headerlink" title="身体"></a>身体</h3><p>每天坚持2km。</p><p>3天完成4组胸和腹，一周休息一天。</p><p>注意体态的纠正。</p><h3 id="后话"><a href="#后话" class="headerlink" title="后话"></a>后话</h3><p> 大三生活才开始，在这最关键的一年要好好努力，为了明年有一个比较好的结果。</p><p>为了更美好的明天。</p>]]></content>
    
    
    <categories>
      
      <category>杂</category>
      
    </categories>
    
    
  </entry>
  
  
  
  
</search>
